{"id":"000500","filename":"ua-uwa-01-stkoz-01-0051.jpg","creator":"Stas Kozljuk","date":"2022-03-07","oblast":"Kharkivska","rayon":"Kharkivskyi","city":"Kharkiv","caption":"07.03.2022, Харків. Станція метро у Салтівському районі Харкова. На той час через постійні обстріли міста частина людей перебралася жити до метрополітену. Однак якщо на центральних станціях проживали по кілька десятків людей, то ближче до спальних районів (районів, де зосереджена висотна житлова забудова), могли жити від 500 до 1,5 тисяч людей.","graphic":0,"location":"Kharkiv"}
