{"filename":"UA-UAWAR-01-SHU-01-0009.jpg","creator":"Serhii Hudak","date":"2022-03-07","week":10,"oblast_en":"Zakarpatska","oblast_ua":"Закарпатська","rayon_en":"Uzhhorodskyi","rayon_ua":"Ужгородський","city_en":"Uzhhorod","city_ua":"Ужгарад","caption_ua":"місто Ужгород, Закарпатська область України.  Юнак відпочиває на матраці в залі одного з спортивних комплексів міста, який  став тимчасовим житлом для людей, що,  рятуючись від російської агресії, опинилися в Ужгороді – найзахіднішому обласному центру України.\n","graphic":0,"tag_id":16,"month":"2022-03-01","id":"000049","ttag":"Civilian sector"}
